mtng/__init__.py
mtng/cli.py
mtng/collect.py
mtng/generate.py
mtng/spec.py
mtng/template/base.aux
mtng/template/base.fdb_latexmk
mtng/template/base.fls
mtng/template/base.log
mtng/template/base.out
mtng/template/base.tex
mtng/template/item.tex
mtng/template/item_context.tex
mtng/template/macros.tex
mtng/template/main.tex
mtng/template/preamble.tex
mtng/template/provides.tex
mtng/template/repo.tex
mtng-0.8.1.dist-info/WHEEL
mtng-0.8.1.dist-info/entry_points.txt
mtng-0.8.1.dist-info/METADATA
mtng-0.8.1.dist-info/RECORD
