Metadata-Version: 2.3
Name: mtng
Version: 0.8.1
Summary: 
Author: Paul Gessinger
Author-email: Paul Gessinger <hello@paulgessinger.com>
Requires-Dist: python-dotenv>=0.17.1
Requires-Dist: jinja2>=3.1.1
Requires-Dist: requests>=2.25.1
Requires-Dist: typer>=0.6.1
Requires-Dist: python-dateutil>=2.8.1
Requires-Dist: aiohttp>=3.7.4
Requires-Dist: gidgethub>=5.0.1
Requires-Dist: pydantic>=1.8.2
Requires-Dist: pyyaml>=6.0.1
Requires-Dist: pytest-asyncio>=0.19.0
Requires-Dist: pytest-dotenv>=0.5.2
Requires-Dist: appdirs>=1.4.4
Requires-Dist: diskcache>=5.4.0
Requires-Dist: rich>=13.4.2
Requires-Dist: pytest>=7.1.2 ; extra == 'dev'
Requires-Dist: black>=23.1.0 ; extra == 'dev'
Requires-Dist: nox>=2022.8.7 ; extra == 'dev'
Requires-Python: >=3.12
Project-URL: homepage, https://github.com/paulgessinger/mtng
Provides-Extra: dev
